pyprogressbarcli/__init__.py
pyprogressbarcli/pyprogressbarcli.py
pyprogressbarcli-1.0.0.dist-info/LICENSE
pyprogressbarcli-1.0.0.dist-info/METADATA
pyprogressbarcli-1.0.0.dist-info/WHEEL
pyprogressbarcli-1.0.0.dist-info/top_level.txt
pyprogressbarcli-1.0.0.dist-info/RECORD
